migrate_config.py
solaredge2mqtt/__init__.py
solaredge2mqtt/__main__.py
solaredge2mqtt/service.py
solaredge2mqtt/config/__init__.py
solaredge2mqtt/config/configuration.yml.example
solaredge2mqtt/config/secrets.yml.example
solaredge2mqtt/core/exceptions.py
solaredge2mqtt/core/models.py
solaredge2mqtt/core/events/__init__.py
solaredge2mqtt/core/events/events.py
solaredge2mqtt/core/influxdb/__init__.py
solaredge2mqtt/core/influxdb/events.py
solaredge2mqtt/core/influxdb/settings.py
solaredge2mqtt/core/influxdb/flux/actual_unit.flux
solaredge2mqtt/core/influxdb/flux/aggregate.flux
solaredge2mqtt/core/influxdb/flux/forecast.flux
solaredge2mqtt/core/influxdb/flux/historic_unit.flux
solaredge2mqtt/core/influxdb/flux/production.flux
solaredge2mqtt/core/influxdb/flux/reduce.flux
solaredge2mqtt/core/influxdb/flux/training_data.flux
solaredge2mqtt/core/influxdb/flux/fixes/fix_0.20.1.flux
solaredge2mqtt/core/influxdb/flux/fixes/import-historic-monitoring_data_1.0.8.flux
solaredge2mqtt/core/influxdb/flux/fixes/refactor_money_fields_1.0.8.flux
solaredge2mqtt/core/logging/__init__.py
solaredge2mqtt/core/logging/models.py
solaredge2mqtt/core/mqtt/__init__.py
solaredge2mqtt/core/mqtt/events.py
solaredge2mqtt/core/mqtt/models.py
solaredge2mqtt/core/mqtt/settings.py
solaredge2mqtt/core/settings/__init__.py
solaredge2mqtt/core/settings/loader.py
solaredge2mqtt/core/settings/migrator.py
solaredge2mqtt/core/settings/models.py
solaredge2mqtt/core/timer/__init__.py
solaredge2mqtt/core/timer/events.py
solaredge2mqtt/services/__init__.py
solaredge2mqtt/services/events.py
solaredge2mqtt/services/http_async.py
solaredge2mqtt/services/models.py
solaredge2mqtt/services/energy/__init__.py
solaredge2mqtt/services/energy/events.py
solaredge2mqtt/services/energy/models.py
solaredge2mqtt/services/energy/settings.py
solaredge2mqtt/services/forecast/__init__.py
solaredge2mqtt/services/forecast/encoders.py
solaredge2mqtt/services/forecast/events.py
solaredge2mqtt/services/forecast/models.py
solaredge2mqtt-2.3.0.dist-info/licenses/LICENSE
solaredge2mqtt-2.3.0.dist-info/METADATA
solaredge2mqtt-2.3.0.dist-info/WHEEL
solaredge2mqtt-2.3.0.dist-info/entry_points.txt
solaredge2mqtt-2.3.0.dist-info/top_level.txt
solaredge2mqtt-2.3.0.dist-info/RECORD
