Metadata-Version: 2.4
Name: solaredge2mqtt
Version: 2.3.0
Summary: Read data from SolarEdge Inverter and publish it to MQTT
Author-email: Johannes Ott <info@johannes-ott.net>
License-Expression: MIT
Project-URL: Homepage, https://github.com/DerOetzi/solaredge2mqtt
Project-URL: Documentation, https://github.com/DerOetzi/solaredge2mqtt/README.md
Project-URL: Repository, https://github.com/DerOetzi/solaredge2mqtt
Project-URL: Issues, https://github.com/DerOetzi/solaredge2mqtt/issues
Keywords: smart home
Classifier: Development Status :: 5 - Production/Stable
Classifier: Topic :: Home Automation
Classifier: Natural Language :: English
Classifier: Programming Language :: Python :: 3 :: Only
Classifier: Programming Language :: Python :: 3.11
Classifier: Programming Language :: Python :: 3.12
Requires-Python: <4,>=3.11
License-File: LICENSE
Requires-Dist: aiocsv==1.4.0
Requires-Dist: aiohttp==3.13.3
Requires-Dist: aiomqtt==2.5.0
Requires-Dist: astral==3.2
Requires-Dist: ephem==4.2
Requires-Dist: influxdb-client==1.50.0
Requires-Dist: jsonref==1.1.0
Requires-Dist: loguru==0.7.3
Requires-Dist: platformdirs==4.5.1
Requires-Dist: pydantic==2.12.5
Requires-Dist: pyjwt==2.10.1
Requires-Dist: pymodbus==3.11.4
Requires-Dist: pyyaml==6.0.3
Requires-Dist: tzlocal==5.3.1
Provides-Extra: dev
Requires-Dist: setuptools-scm[toml]>=8; extra == "dev"
Requires-Dist: ruff; extra == "dev"
Requires-Dist: tomli; extra == "dev"
Requires-Dist: pytest==9.0.2; extra == "dev"
Requires-Dist: pytest-asyncio==1.3.0; extra == "dev"
Requires-Dist: pytest-cov==7.0.0; extra == "dev"
Provides-Extra: forecast
Requires-Dist: numpy==2.4.1; extra == "forecast"
Requires-Dist: pandas==3.0.0; extra == "forecast"
Requires-Dist: scikit-learn==1.8.0; extra == "forecast"
Requires-Dist: scipy==1.17.0; extra == "forecast"
Dynamic: license-file
